jube/metadata.py
jube/cli/__init__.py
jube_cli-0.0.1.dist-info/METADATA
jube_cli-0.0.1.dist-info/WHEEL
jube_cli-0.0.1.dist-info/entry_points.txt
jube_cli-0.0.1.dist-info/RECORD
