Metadata-Version: 2.3
Name: jube_cli
Version: 0.0.1
Summary: A helper script for the jube project
Project-URL: Documentation, https://github.com/FZJ-JSC/jube
Author-email: Jayesh Badwaik <j.badwaik@fz-juelich.de>
Requires-Dist: semver
